num2word.py
num2word-1.0.1.dist-info/LICENSE.txt
num2word-1.0.1.dist-info/METADATA
num2word-1.0.1.dist-info/WHEEL
num2word-1.0.1.dist-info/top_level.txt
num2word-1.0.1.dist-info/RECORD
