Metadata-Version: 2.1
Name: num2word
Version: 1.0.1
Summary: Convert any number to word
Home-page: https://github.com/MUKESHSIHAG/python_library_num2word
Author: Mukesh Kumar
Author-email: sihagmukesh22@gmail.com
License: UNKNOWN
Platform: UNKNOWN
Classifier: Programming Language :: Python :: 2
Classifier: Programming Language :: Python :: 2.7
Classifier: Programming Language :: Python :: 3
Classifier: Programming Language :: Python :: 3.5
Classifier: Programming Language :: Python :: 3.6
Classifier: Programming Language :: Python :: 3.7
Classifier: License :: OSI Approved :: GNU General Public License v2 or later (GPLv2+)
Classifier: Operating System :: OS Independent
